epyt/__init__.py
epyt/epanet.py
epyt/__pycache__/__init__.cpython-312.pyc
epyt/__pycache__/__init__.cpython-39.pyc
epyt/__pycache__/epanet.cpython-312.pyc
epyt/__pycache__/epanet.cpython-39.pyc
epyt/examples/README.md
epyt/examples/__init__.py
epyt/examples/notebooks/EX10_close_pipes_during_sim.ipynb
epyt/examples/notebooks/EX11_assing_new_curve_pump.ipynb
epyt/examples/notebooks/EX12_add_cvpipe.ipynb
epyt/examples/notebooks/EX13_hydraulic_and_quality_analysis.ipynb
epyt/examples/notebooks/EX14_create_multiple_scenarios.ipynb
epyt/examples/notebooks/EX15_add_multiple_controls_pipestatus.ipynb
epyt/examples/notebooks/EX16_change_status_pipes.ipynb
epyt/examples/notebooks/EX17a_external_controls.ipynb
epyt/examples/notebooks/EX17b_external_controls.ipynb
epyt/examples/notebooks/EX18_Pressure_driven_analysis_option.ipynb
epyt/examples/notebooks/EX19_Overflow_option_for_tanks.ipynb
epyt/examples/notebooks/EX1_Plot_network_topology.ipynb
epyt/examples/notebooks/EX20_Change_connection_links.ipynb
epyt/examples/notebooks/EX21_set_node_name_ids.ipynb
epyt/examples/notebooks/EX2_Hydraulic_analysis.ipynb
epyt/examples/notebooks/EX3_Quality_analysis.ipynb
epyt/examples/notebooks/EX4_Plot_time_series.ipynb
epyt/examples/notebooks/EX5_Plot_values_parameters.ipynb
epyt/examples/notebooks/EX6_load_two_inp_files.ipynb
epyt/examples/notebooks/EX7_Set_Pump_Curves.ipynb
epyt/examples/notebooks/EX9_compare_simulations.ipynb
epyt/examples/notebooks/Net1_pressures.gif
epyt/examples/notebooks/Plt_EX1_Create_Flow_gif.ipynb
epyt/examples/notebooks/Plt_EX2_Create_Pressure_gif.ipynb
epyt/examples/notebooks/TESTING.inp
epyt/examples/notebooks/TESTING.txt
epyt/examples/notebooks/Toolkit_EX2_Hydrant_rating_curve.ipynb
epyt/examples/notebooks/Toolkit_EX3_Minimum_chlorine_residual.ipynb
epyt/examples/notebooks/Toolkit_EX4_Network_Building.ipynb
epyt/examples/notebooks/Toolkit_api_EX1_using_EN_functions.ipynb
epyt/examples/notebooks/example2.inp
epyt/examples/notebooks/net1_overflow.inp
epyt-1.2.3.dist-info/LICENSE.md
epyt-1.2.3.dist-info/METADATA
epyt-1.2.3.dist-info/WHEEL
epyt-1.2.3.dist-info/top_level.txt
epyt-1.2.3.dist-info/RECORD
