Metadata-Version: 2.1
Name: epyt
Version: 1.2.3
Summary: EPyT: An EPANET-Python Toolkit for Smart Water Network Simulations. The EPyT is inspired by the EPANET-Matlab Toolkit.
Home-page: https://github.com/OpenWaterAnalytics/EPyT
Author: Marios S. Kyriakou
Author-email: kiriakou.marios@ucy.ac.cy
Project-URL: Bug Tracker, https://github.com/OpenWaterAnalytics/EPyT/issues
Keywords: epanet,water,networks,hydraulics,quality,simulations,emt,epanet matlab toolkit
Classifier: Programming Language :: Python :: 3.8
Classifier: Programming Language :: Python :: 3.9
Classifier: Programming Language :: Python :: 3.10
Classifier: Programming Language :: Python :: 3.11
Classifier: Programming Language :: Python :: 3.12
Classifier: Programming Language :: Python :: 3.13
Classifier: Programming Language :: Python
Classifier: License :: OSI Approved :: European Union Public Licence 1.2 (EUPL 1.2)
Classifier: Operating System :: OS Independent
Requires-Python: >=3.8
License-File: LICENSE.md
Requires-Dist: numpy
Requires-Dist: matplotlib
Requires-Dist: pandas
Requires-Dist: xlsxwriter
Requires-Dist: setuptools
